brazil_monthly_deaths/__init__.py
brazil_monthly_deaths/dataframes.py
brazil_monthly_deaths/exceptions.py
brazil_monthly_deaths/update_new_data.py
brazil_monthly_deaths/web_scraping.py
brazil_monthly_deaths/data/__init__.py
brazil_monthly_deaths/data/data_2015.csv
brazil_monthly_deaths/data/data_2016.csv
brazil_monthly_deaths/data/data_2017.csv
brazil_monthly_deaths/data/data_2018.csv
brazil_monthly_deaths/data/data_2019.csv
brazil_monthly_deaths/data/data_2020.csv
brazil_monthly_deaths-1.4.0.dist-info/LICENSE
brazil_monthly_deaths-1.4.0.dist-info/METADATA
brazil_monthly_deaths-1.4.0.dist-info/WHEEL
brazil_monthly_deaths-1.4.0.dist-info/top_level.txt
brazil_monthly_deaths-1.4.0.dist-info/RECORD
