Metadata-Version: 2.1
Name: brazil-monthly-deaths
Version: 1.4.0
Summary: Brazil deaths by city as pandas dataframe or csv file
Home-page: https://github.com/pedrobern/brazil-monthly-deaths-by-city
Author: pedrobern
Author-email: pedrobermoreira@gmail.com
Maintainer: pedrobern
License: MIT
Project-URL: Documentation, https://github.com/pedrobern/brazil-monthly-deaths-by-city
Project-URL: Issues, https://github.com/pedrobern/brazil-monthly-deaths-by-city/issues
Keywords: brazil death rate data science
Platform: UNKNOWN
Classifier: Development Status :: 4 - Beta
Classifier: Environment :: Web Environment
Classifier: Intended Audience :: Developers
Classifier: License :: OSI Approved :: MIT License
Classifier: Operating System :: OS Independent
Classifier: Programming Language :: Python
Classifier: Programming Language :: Python :: 3.6
Classifier: Programming Language :: Python :: 3.7
Classifier: Programming Language :: Python :: 3.8
Requires-Dist: pandas (>=1.0.0)
Requires-Dist: numpy (>=1.18.0)
Requires-Dist: selenium (>=3.141.0)
Provides-Extra: dev
Requires-Dist: black (==19.10b0) ; extra == 'dev'
Requires-Dist: flake8 (==3.8.1) ; extra == 'dev'
Requires-Dist: pytest (>=5.4.2) ; extra == 'dev'
Requires-Dist: pytest-cov (>=2.8.1) ; extra == 'dev'
Requires-Dist: coveralls (>=2.0.0) ; extra == 'dev'
Provides-Extra: test
Requires-Dist: pytest (>=5.4.2) ; extra == 'test'
Requires-Dist: pytest-cov (>=2.8.1) ; extra == 'test'
Requires-Dist: coveralls (>=2.0.0) ; extra == 'test'
